[
  {
    "titulo": "El postre más goloso del mundo listo en minutos en el microondas",
    "url": "https://bonviveur.com/es/actualidad/el-postre-mas-goloso-del-mundo-listo-en-minutos-en-el-microondas",
    "imagen": "https://imag.bonviveur.com/brownie-al-microondas-listo-para-comer.jpg",
    "fecha": "2026-05-31T11:46:13.000Z"
  },
  {
    "titulo": "9 recetas con piñones: propuestas imprescindibles para disfrutar de todo el sabor de este gran fruto seco",
    "url": "https://bonviveur.com/es/recetas/lista/pinones/",
    "imagen": "https://imag.bonviveur.com/pinones.jpg",
    "fecha": "2026-05-31T07:11:00.000Z"
  },
  {
    "titulo": "11 recetas de la cocina cajún y criolla para disfrutar del mejor sabor de Luisiana",
    "url": "https://bonviveur.com/es/recetas/lista/cocina-cajun/",
    "imagen": "https://imag.bonviveur.com/cajun.jpg",
    "fecha": "2026-05-31T06:35:37.000Z"
  },
  {
    "titulo": "Pollo cajún: una receta facilísima y muy sabrosa al más puro estilo de Louisiana",
    "url": "https://bonviveur.com/es/recetas/pollo-cajun",
    "imagen": "https://imag.bonviveur.com/pollo-cajun-listo-para-servir.jpg",
    "fecha": "2026-05-31T06:35:36.000Z"
  },
  {
    "titulo": "Los restaurantes de Sevilla con Estrellas Michelin 2026",
    "url": "https://bonviveur.com/es/noticias/restaurantes-de-sevilla-con-estrellas-michelin",
    "imagen": "https://imag.bonviveur.com/restaurantes-de-sevilla-con-estrellas-michelin.jpg",
    "fecha": "2026-05-31T06:10:00.000Z"
  },
  {
    "titulo": "Bizcocho de nísperos: una sabrosa reinvención del postre tradicional con esta fruta tan veraniega",
    "url": "https://bonviveur.com/es/recetas/bizcocho-de-nisperos",
    "imagen": "https://imag.bonviveur.com/textura-del-bizcocho-de-nisperos.jpg",
    "fecha": "2026-05-30T09:03:00.000Z"
  },
  {
    "titulo": "10 recetas con café: ideas sorprendentes para dar un toque de sofisticación a tus mejores sobremesas",
    "url": "https://bonviveur.com/es/recetas/lista/cafe/",
    "imagen": "https://imag.bonviveur.com/con-cafe.jpg",
    "fecha": "2026-05-30T08:03:00.000Z"
  },
  {
    "titulo": "Recetas muy ricas y fáciles de hacer para el día a día: menú semanal del 1 al 7 de junio",
    "url": "https://bonviveur.com/es/actualidad/menu-semanal-del-1-al-7-de-junio",
    "imagen": "https://imag.bonviveur.com/menu-semanal-del-1-al-7-de-junio.jpg",
    "fecha": "2026-05-30T07:30:00.000Z"
  },
  {
    "titulo": "Los restaurantes de Cantabria con Estrellas Michelin 2026",
    "url": "https://bonviveur.com/es/noticias/restaurantes-de-cantabria-con-estrellas-michelin",
    "imagen": "https://imag.bonviveur.com/restaurantes-de-cantabria-con-estrellas-michelin.jpg",
    "fecha": "2026-05-30T06:30:00.000Z"
  },
  {
    "titulo": "Pan para hot dog: la receta para hacerlo totalmente casero de forma sencilla",
    "url": "https://bonviveur.com/es/recetas/pan-para-hot-dog",
    "imagen": "https://imag.bonviveur.com/pan-para-hot-dog-casero.jpg",
    "fecha": "2026-05-29T07:00:00.000Z"
  },
  {
    "titulo": "Los restaurantes de Castilla y León con Estrellas Michelin 2026",
    "url": "https://bonviveur.com/es/noticias/restaurantes-de-castilla-y-leon-con-estrellas-michelin",
    "imagen": "https://imag.bonviveur.com/restaurantes-de-castilla-y-leon-con-estrellas-michelin.jpg",
    "fecha": "2026-05-29T05:31:00.000Z"
  },
  {
    "titulo": "Capirotada: la receta del tradicional postre mexicano de Cuaresma a base de pan y miel de piloncillo",
    "url": "https://bonviveur.com/es/recetas/capirotada",
    "imagen": "https://imag.bonviveur.com/capirotada.jpg",
    "fecha": "2026-05-29T05:23:00.000Z"
  },
  {
    "titulo": "8 recetas de tartas Tatin: desde la clásica de manzana a las versiones más inesperadas",
    "url": "https://bonviveur.com/es/recetas/lista/tarta-tatin/",
    "imagen": "https://imag.bonviveur.com/tartas-tatin.jpg",
    "fecha": "2026-05-29T05:22:00.000Z"
  }
]
