{
  "generado": "2026-06-30T03:31:37.849Z",
  "limite": 50,
  "total": 46229,
  "noticias": [
    {
      "titulo": "El tiempo en Monesterio: previsión meteorológica para hoy, martes 30 de junio",
      "url": "https://www.elperiodicoextremadura.com/tiempo/2026/06/30/tiempo-monesterio-prevision-meteorologica-hoy-131954210.html",
      "imagen": "https://estaticos-cdn.prensaiberica.es/clip/cd6582a2-27fe-434f-970f-155f0184b89d_16-9-aspect-ratio_default_0_x600y225.jpg",
      "fecha": "2026-06-30T02:39:50.000Z",
      "fuenteId": "el-periodico-extremadura",
      "fuenteTitle": "El Periódico Extremadura",
      "categorias": [
        "local"
      ],
      "idioma": "es"
    },
    {
      "titulo": "El tiempo en Fregenal de la Sierra: previsión meteorológica para hoy, martes 30 de junio",
      "url": "https://www.elperiodicoextremadura.com/tiempo/2026/06/30/tiempo-fregenal-sierra-prevision-meteorologica-131954196.html",
      "imagen": "https://estaticos-cdn.prensaiberica.es/clip/24153282-c673-4cf7-9b95-f0f3fe2101f0_16-9-aspect-ratio_default_0_x600y225.jpg",
      "fecha": "2026-06-30T02:38:32.000Z",
      "fuenteId": "el-periodico-extremadura",
      "fuenteTitle": "El Periódico Extremadura",
      "categorias": [
        "local"
      ],
      "idioma": "es"
    },
    {
      "titulo": "El tiempo en Olivenza: previsión meteorológica para hoy, martes 30 de junio",
      "url": "https://www.elperiodicoextremadura.com/tiempo/2026/06/30/tiempo-olivenza-prevision-meteorologica-hoy-131954194.html",
      "imagen": "https://estaticos-cdn.prensaiberica.es/clip/ab306ec1-17d8-46c9-a54d-bec7186c1c34_16-9-aspect-ratio_default_0_x600y225.jpg",
      "fecha": "2026-06-30T02:38:21.000Z",
      "fuenteId": "el-periodico-extremadura",
      "fuenteTitle": "El Periódico Extremadura",
      "categorias": [
        "local"
      ],
      "idioma": "es"
    },
    {
      "titulo": "El tiempo en Moraleja: previsión meteorológica para hoy, martes 30 de junio",
      "url": "https://www.elperiodicoextremadura.com/tiempo/2026/06/30/tiempo-moraleja-prevision-meteorologica-hoy-131954190.html",
      "imagen": "https://estaticos-cdn.prensaiberica.es/clip/01154179-3d75-4cd9-bf25-b6d68e5001f3_16-9-aspect-ratio_default_0_x600y225.jpg",
      "fecha": "2026-06-30T02:37:59.000Z",
      "fuenteId": "el-periodico-extremadura",
      "fuenteTitle": "El Periódico Extremadura",
      "categorias": [
        "local"
      ],
      "idioma": "es"
    },
    {
      "titulo": "El tiempo en Azuaga: previsión meteorológica para hoy, martes 30 de junio",
      "url": "https://www.elperiodicoextremadura.com/tiempo/2026/06/30/tiempo-azuaga-prevision-meteorologica-hoy-131954188.html",
      "imagen": "https://estaticos-cdn.prensaiberica.es/clip/eb2d4673-9569-4648-9253-c311758d2d43_16-9-aspect-ratio_default_0_x600y225.jpg",
      "fecha": "2026-06-30T02:37:49.000Z",
      "fuenteId": "el-periodico-extremadura",
      "fuenteTitle": "El Periódico Extremadura",
      "categorias": [
        "local"
      ],
      "idioma": "es"
    },
    {
      "titulo": "El tiempo en Coria: previsión meteorológica para hoy, martes 30 de junio",
      "url": "https://www.elperiodicoextremadura.com/tiempo/2026/06/30/tiempo-coria-prevision-meteorologica-hoy-131954179.html",
      "imagen": "https://estaticos-cdn.prensaiberica.es/clip/1d4215d7-25b9-417e-97d8-72da059df3a7_16-9-aspect-ratio_default_0_x600y225.jpg",
      "fecha": "2026-06-30T02:37:27.000Z",
      "fuenteId": "el-periodico-extremadura",
      "fuenteTitle": "El Periódico Extremadura",
      "categorias": [
        "local"
      ],
      "idioma": "es"
    },
    {
      "titulo": "El tiempo en Arroyo de la Luz: previsión meteorológica para hoy, martes 30 de junio",
      "url": "https://www.elperiodicoextremadura.com/tiempo/2026/06/30/tiempo-arroyo-luz-prevision-meteorologica-131954173.html",
      "imagen": "https://estaticos-cdn.prensaiberica.es/clip/d03cb819-54b7-491d-a5dc-be3ecd58dd75_16-9-aspect-ratio_default_0_x600y225.jpg",
      "fecha": "2026-06-30T02:37:16.000Z",
      "fuenteId": "el-periodico-extremadura",
      "fuenteTitle": "El Periódico Extremadura",
      "categorias": [
        "local"
      ],
      "idioma": "es"
    },
    {
      "titulo": "El tiempo en Casar de Cáceres: previsión meteorológica para hoy, martes 30 de junio",
      "url": "https://www.elperiodicoextremadura.com/tiempo/2026/06/30/tiempo-casar-caceres-prevision-meteorologica-131954170.html",
      "imagen": "https://estaticos-cdn.prensaiberica.es/clip/c0c06e3f-03df-479d-a596-c88814249b24_16-9-aspect-ratio_default_0_x600y225.jpg",
      "fecha": "2026-06-30T02:37:06.000Z",
      "fuenteId": "el-periodico-extremadura",
      "fuenteTitle": "El Periódico Extremadura",
      "categorias": [
        "local"
      ],
      "idioma": "es"
    },
    {
      "titulo": "El tiempo en Malpartida de Cáceres: previsión meteorológica para hoy, martes 30 de junio",
      "url": "https://www.elperiodicoextremadura.com/tiempo/2026/06/30/tiempo-malpartida-caceres-prevision-meteorologica-131954168.html",
      "imagen": "https://estaticos-cdn.prensaiberica.es/clip/df473d20-ba85-4b9e-924e-0c3c25c3889f_16-9-aspect-ratio_default_0_x600y225.jpg",
      "fecha": "2026-06-30T02:36:55.000Z",
      "fuenteId": "el-periodico-extremadura",
      "fuenteTitle": "El Periódico Extremadura",
      "categorias": [
        "local"
      ],
      "idioma": "es"
    },
    {
      "titulo": "El tiempo en San Vicente de Alcántara: previsión meteorológica para hoy, martes 30 de junio",
      "url": "https://www.elperiodicoextremadura.com/tiempo/2026/06/30/tiempo-san-vicente-alcantara-prevision-131954166.html",
      "imagen": "https://estaticos-cdn.prensaiberica.es/clip/a9ab1e34-b8a1-4f10-b32f-580e8296d821_16-9-aspect-ratio_default_0_x600y225.jpg",
      "fecha": "2026-06-30T02:36:44.000Z",
      "fuenteId": "el-periodico-extremadura",
      "fuenteTitle": "El Periódico Extremadura",
      "categorias": [
        "local"
      ],
      "idioma": "es"
    },
    {
      "titulo": "El tiempo en Valencia de Alcántara: previsión meteorológica para hoy, martes 30 de junio",
      "url": "https://www.elperiodicoextremadura.com/tiempo/2026/06/30/tiempo-valencia-alcantara-prevision-meteorologica-131954164.html",
      "imagen": "https://estaticos-cdn.prensaiberica.es/clip/590fd450-911e-47fe-896a-930f93589f9e_16-9-aspect-ratio_default_0_x600y225.jpg",
      "fecha": "2026-06-30T02:36:33.000Z",
      "fuenteId": "el-periodico-extremadura",
      "fuenteTitle": "El Periódico Extremadura",
      "categorias": [
        "local"
      ],
      "idioma": "es"
    },
    {
      "titulo": "El tiempo en Cáceres: previsión meteorológica para hoy, martes 30 de junio",
      "url": "https://www.elperiodicoextremadura.com/tiempo/2026/06/30/tiempo-caceres-prevision-meteorologica-hoy-131954162.html",
      "imagen": "https://estaticos-cdn.prensaiberica.es/clip/a1e765ae-7083-433e-acc1-443b9a845a2c_16-9-aspect-ratio_default_0_x600y225.jpg",
      "fecha": "2026-06-30T02:36:22.000Z",
      "fuenteId": "el-periodico-extremadura",
      "fuenteTitle": "El Periódico Extremadura",
      "categorias": [
        "local"
      ],
      "idioma": "es"
    },
    {
      "titulo": "El tiempo en Alburquerque: previsión meteorológica para hoy, martes 30 de junio",
      "url": "https://www.elperiodicoextremadura.com/tiempo/2026/06/30/tiempo-alburquerque-prevision-meteorologica-hoy-131954160.html",
      "imagen": "https://estaticos-cdn.prensaiberica.es/clip/d0945349-fbaa-47f5-8ac0-caceaca79a32_16-9-aspect-ratio_default_0_x600y225.jpg",
      "fecha": "2026-06-30T02:36:11.000Z",
      "fuenteId": "el-periodico-extremadura",
      "fuenteTitle": "El Periódico Extremadura",
      "categorias": [
        "local"
      ],
      "idioma": "es"
    },
    {
      "titulo": "El tiempo en Almendralejo: previsión meteorológica para hoy, martes 30 de junio",
      "url": "https://www.elperiodicoextremadura.com/tiempo/2026/06/30/tiempo-almendralejo-prevision-meteorologica-hoy-131954158.html",
      "imagen": "https://estaticos-cdn.prensaiberica.es/clip/e23bb28b-59b0-4c07-ab6e-cdc7d2ae5280_16-9-aspect-ratio_default_0_x600y225.jpg",
      "fecha": "2026-06-30T02:35:59.000Z",
      "fuenteId": "el-periodico-extremadura",
      "fuenteTitle": "El Periódico Extremadura",
      "categorias": [
        "local"
      ],
      "idioma": "es"
    },
    {
      "titulo": "El tiempo en Talavera la Real: previsión meteorológica para hoy, martes 30 de junio",
      "url": "https://www.elperiodicoextremadura.com/tiempo/2026/06/30/tiempo-talavera-real-prevision-meteorologica-131954156.html",
      "imagen": "https://estaticos-cdn.prensaiberica.es/clip/ed90c73f-c21b-4898-bce0-54e61659997a_16-9-aspect-ratio_default_0_x600y225.jpg",
      "fecha": "2026-06-30T02:35:49.000Z",
      "fuenteId": "el-periodico-extremadura",
      "fuenteTitle": "El Periódico Extremadura",
      "categorias": [
        "local"
      ],
      "idioma": "es"
    },
    {
      "titulo": "El tiempo en Badajoz: previsión meteorológica para hoy, martes 30 de junio",
      "url": "https://www.elperiodicoextremadura.com/tiempo/2026/06/30/tiempo-badajoz-prevision-meteorologica-hoy-131954154.html",
      "imagen": "https://estaticos-cdn.prensaiberica.es/clip/e3cd548b-6ece-49d0-b5b4-4897b71e90ec_16-9-aspect-ratio_default_0_x600y225.jpg",
      "fecha": "2026-06-30T02:35:38.000Z",
      "fuenteId": "el-periodico-extremadura",
      "fuenteTitle": "El Periódico Extremadura",
      "categorias": [
        "local"
      ],
      "idioma": "es"
    },
    {
      "titulo": "El tiempo en Aceuchal: previsión meteorológica para hoy, martes 30 de junio",
      "url": "https://www.elperiodicoextremadura.com/tiempo/2026/06/30/tiempo-aceuchal-prevision-meteorologica-hoy-131954152.html",
      "imagen": "https://estaticos-cdn.prensaiberica.es/clip/613d38c6-078b-43b8-a0fc-18247c87ecc7_16-9-aspect-ratio_default_0_x600y225.jpg",
      "fecha": "2026-06-30T02:35:26.000Z",
      "fuenteId": "el-periodico-extremadura",
      "fuenteTitle": "El Periódico Extremadura",
      "categorias": [
        "local"
      ],
      "idioma": "es"
    },
    {
      "titulo": "El tiempo en Villafranca de los Barros: previsión meteorológica para hoy, martes 30 de junio",
      "url": "https://www.elperiodicoextremadura.com/tiempo/2026/06/30/tiempo-villafranca-barros-prevision-meteorologica-131954150.html",
      "imagen": "https://estaticos-cdn.prensaiberica.es/clip/71509d36-bcc6-42c7-ac63-f90d3f078f95_16-9-aspect-ratio_default_0_x600y225.jpg",
      "fecha": "2026-06-30T02:35:15.000Z",
      "fuenteId": "el-periodico-extremadura",
      "fuenteTitle": "El Periódico Extremadura",
      "categorias": [
        "local"
      ],
      "idioma": "es"
    },
    {
      "titulo": "El tiempo en Santa Marta: previsión meteorológica para hoy, martes 30 de junio",
      "url": "https://www.elperiodicoextremadura.com/tiempo/2026/06/30/tiempo-santa-marta-prevision-meteorologica-131954146.html",
      "imagen": "https://estaticos-cdn.prensaiberica.es/clip/3e72285d-1984-459a-9041-0da60e432ca0_16-9-aspect-ratio_default_0_x600y225.jpg",
      "fecha": "2026-06-30T02:35:03.000Z",
      "fuenteId": "el-periodico-extremadura",
      "fuenteTitle": "El Periódico Extremadura",
      "categorias": [
        "local"
      ],
      "idioma": "es"
    },
    {
      "titulo": "El tiempo en Fuente del Maestre: previsión meteorológica para hoy, martes 30 de junio",
      "url": "https://www.elperiodicoextremadura.com/tiempo/2026/06/30/tiempo-fuente-maestre-prevision-meteorologica-131954143.html",
      "imagen": "https://estaticos-cdn.prensaiberica.es/clip/7f882277-6bfe-44f5-9a69-05613ac48883_16-9-aspect-ratio_default_0_x600y225.jpg",
      "fecha": "2026-06-30T02:34:52.000Z",
      "fuenteId": "el-periodico-extremadura",
      "fuenteTitle": "El Periódico Extremadura",
      "categorias": [
        "local"
      ],
      "idioma": "es"
    },
    {
      "titulo": "Vishay fija el precio de su oferta de acciones por 750 millones de dólares a 50 dólares por acción",
      "url": "https://es.investing.com/news/company-news/vishay-fija-el-precio-de-su-oferta-de-acciones-por-750-millones-de-dolares-a-50-dolares-por-accion-93CH-3721620",
      "imagen": "https://i-invdn-com.investing.com/news/world_news_2_108x81.jpg",
      "fecha": "2026-06-30T02:30:11.000Z",
      "fuenteId": "investing-es-noticias",
      "fuenteTitle": "Investing.com España - Noticias",
      "categorias": [
        "economia"
      ],
      "idioma": "es"
    },
    {
      "titulo": "Venezuela: por qué hay tantas réplicas después de los terremotos y cuánto tiempo pueden durar",
      "url": "https://www.bbc.com/mundo/articles/cx2jw1kz293o?at_medium=RSS&at_campaign=rss",
      "imagen": "https://ichef.bbci.co.uk/ace/ws/240/cpsprodpb/e6bc/live/0f966900-742a-11f1-aef0-ab619497e70e.png",
      "fecha": "2026-06-30T02:30:08.000Z",
      "fuenteId": "bbc-mundo",
      "fuenteTitle": "BBC News Mundo",
      "categorias": [
        "internacional",
        "actualidad"
      ],
      "idioma": "es"
    },
    {
      "titulo": "El Banco de la Reserva de Australia está listo para subir los tipos de interés",
      "url": "https://es.investing.com/news/economy-news/el-banco-de-la-reserva-de-australia-esta-listo-para-subir-los-tipos-de-interes-3721619",
      "imagen": "https://i-invdn-com.investing.com/news/world_news_2_108x81.jpg",
      "fecha": "2026-06-30T02:23:27.000Z",
      "fuenteId": "investing-es-noticias",
      "fuenteTitle": "Investing.com España - Noticias",
      "categorias": [
        "economia"
      ],
      "idioma": "es"
    },
    {
      "titulo": "Declarado día de fiesta nacional",
      "url": "https://www.marca.com/futbol/mundial/2026/06/30/paraguay-llora-felicidad.html",
      "imagen": "https://e01-xlk-ue-marca.uecdn.es/files/article_main_microformat/uploads/2026/06/30/6a4324ee91584.jpeg",
      "fecha": "2026-06-30T02:11:26.000Z",
      "fuenteId": "marca",
      "fuenteTitle": "Marca",
      "categorias": [
        "deportes"
      ],
      "idioma": "es"
    },
    {
      "titulo": "El yen japonés cae a mínimos de 1986 ante posible intervención",
      "url": "https://es.investing.com/news/forex-news/el-yen-japones-cae-a-minimos-de-1986-ante-posible-intervencion-3721617",
      "imagen": "https://i-invdn-com.investing.com/news/world_news_2_108x81.jpg",
      "fecha": "2026-06-30T02:07:49.000Z",
      "fuenteId": "investing-es-noticias",
      "fuenteTitle": "Investing.com España - Noticias",
      "categorias": [
        "economia"
      ],
      "idioma": "es"
    },
    {
      "titulo": "Terremotos en Venezuela: rescatistas buscan sobrevivientes; la comunidad ora frente a las ruinas",
      "url": "https://www.france24.com/es/video/20260630-terremotos-en-venezuela-rescatistas-buscan-sobrevivientes-la-comunidad-ora-frente-a-las-ruinas",
      "imagen": "https://s.france24.com/media/display/212f5770-7426-11f1-8644-005056bf30b7/w:1024/p:16x9/ES-20260629-200531-200927-CS.jpg",
      "fecha": "2026-06-30T02:06:56.000Z",
      "fuenteId": "france24-espanol",
      "fuenteTitle": "France 24 Español",
      "categorias": [
        "internacional",
        "politica"
      ],
      "idioma": "es"
    },
    {
      "titulo": "02:50 | 29 JUN 2026 | TIEMPO DE JUEGO",
      "url": "https://www.cope.es/programas/tiempo-de-juego/horas-completas/02-50-29-jun-2026-juego-20260630_3394055.html",
      "imagen": "",
      "fecha": "2026-06-30T02:06:19.000Z",
      "fuenteId": "cope-extremadura",
      "fuenteTitle": "COPE Extremadura",
      "categorias": [
        "local"
      ],
      "idioma": "es"
    },
    {
      "titulo": "Rusia enfrenta falta de combustible tras ofensiva ucraniana contra sus refinerías",
      "url": "https://www.france24.com/es/programas/econom%C3%ADa/20260630-rusia-enfrenta-falta-de-combustible-tras-ofensiva-ucraniana-contra-sus-refiner%C3%ADas",
      "imagen": "https://s.france24.com/media/display/d46cc2ba-7425-11f1-960b-005056bf30b7/w:1024/p:16x9/AP26121420696481.jpg",
      "fecha": "2026-06-30T02:02:31.000Z",
      "fuenteId": "france24-espanol",
      "fuenteTitle": "France 24 Español",
      "categorias": [
        "internacional",
        "politica"
      ],
      "idioma": "es"
    },
    {
      "titulo": "Las lágrimas del goleador Enciso: \"Veía el fútbol con mi abuelo, le mando un beso en el cielo\"",
      "url": "https://www.mundodeportivo.com/futbol/mundial/20260630/1004200983/lagrimas-goleador-enciso-veia-futbol-mi-abuelo-le-mando-beso-cielo.html",
      "imagen": "https://imagenes2.mundodeportivo.com/files/og_thumbnail/uploads/2026/06/30/6a43231ee05a9.jpeg",
      "fecha": "2026-06-30T02:01:26.000Z",
      "fuenteId": "mundo-deportivo",
      "fuenteTitle": "Mundo Deportivo",
      "categorias": [
        "deportes"
      ],
      "idioma": "es"
    },
    {
      "titulo": "El tiempo en Montehermoso: previsión meteorológica para hoy, martes 30 de junio",
      "url": "https://www.elperiodicoextremadura.com/tiempo/2026/06/30/tiempo-montehermoso-prevision-meteorologica-hoy-131953685.html",
      "imagen": "https://estaticos-cdn.prensaiberica.es/clip/0b6009f8-311d-4547-8f42-11d46ae4d146_16-9-aspect-ratio_default_0_x600y225.jpg",
      "fecha": "2026-06-30T02:00:08.000Z",
      "fuenteId": "el-periodico-extremadura",
      "fuenteTitle": "El Periódico Extremadura",
      "categorias": [
        "local"
      ],
      "idioma": "es"
    },
    {
      "titulo": "Los pueblos ganan habitantes y emprendedores: \"Internet me permite estar en toda España\"",
      "url": "https://www.elperiodicoextremadura.com/economia/2026/06/30/pueblos-ganan-habitantes-emprendedores-internet-131953678.html",
      "imagen": "https://estaticos-cdn.prensaiberica.es/clip/5b0fd51b-064a-4966-8d5b-e44a721a76db_16-9-aspect-ratio_default_0_x800y302.jpg",
      "fecha": "2026-06-30T02:00:00.000Z",
      "fuenteId": "el-periodico-extremadura",
      "fuenteTitle": "El Periódico Extremadura",
      "categorias": [
        "local"
      ],
      "idioma": "es"
    },
    {
      "titulo": "Horóscopo diario de hoy, martes 30 de junio de 2026: predicción para todos los signos del Zodíaco",
      "url": "https://www.marie-claire.es/horoscopo/horoscopo-diario-30-junio-2026.html",
      "imagen": "",
      "fecha": "2026-06-30T02:00:00.000Z",
      "fuenteId": "marie-claire-espana",
      "fuenteTitle": "Marie Claire España",
      "categorias": [
        "moda"
      ],
      "idioma": "es"
    },
    {
      "titulo": "El tiempo en Hervás: previsión meteorológica para hoy, martes 30 de junio",
      "url": "https://www.elperiodicoextremadura.com/tiempo/2026/06/30/tiempo-hervas-prevision-meteorologica-hoy-131953661.html",
      "imagen": "https://estaticos-cdn.prensaiberica.es/clip/c5cfe250-5d97-4539-9e29-59c895026a78_16-9-aspect-ratio_default_0_x600y225.jpg",
      "fecha": "2026-06-30T01:59:55.000Z",
      "fuenteId": "el-periodico-extremadura",
      "fuenteTitle": "El Periódico Extremadura",
      "categorias": [
        "local"
      ],
      "idioma": "es"
    },
    {
      "titulo": "El tiempo en Malpartida de Plasencia: previsión meteorológica para hoy, martes 30 de junio",
      "url": "https://www.elperiodicoextremadura.com/tiempo/2026/06/30/tiempo-malpartida-plasencia-prevision-meteorologica-131953659.html",
      "imagen": "https://estaticos-cdn.prensaiberica.es/clip/0e9330da-98bf-4181-a5a2-b2885c2e8ba4_16-9-aspect-ratio_default_0_x600y225.jpg",
      "fecha": "2026-06-30T01:59:44.000Z",
      "fuenteId": "el-periodico-extremadura",
      "fuenteTitle": "El Periódico Extremadura",
      "categorias": [
        "local"
      ],
      "idioma": "es"
    },
    {
      "titulo": "El tiempo en Plasencia: previsión meteorológica para hoy, martes 30 de junio",
      "url": "https://www.elperiodicoextremadura.com/tiempo/2026/06/30/tiempo-plasencia-prevision-meteorologica-hoy-131953657.html",
      "imagen": "https://estaticos-cdn.prensaiberica.es/clip/05c9a190-b530-40d0-aa65-68911284ef5f_16-9-aspect-ratio_default_0_x600y225.jpg",
      "fecha": "2026-06-30T01:59:33.000Z",
      "fuenteId": "el-periodico-extremadura",
      "fuenteTitle": "El Periódico Extremadura",
      "categorias": [
        "local"
      ],
      "idioma": "es"
    },
    {
      "titulo": "El tiempo en Jaraíz de la Vera: previsión meteorológica para hoy, martes 30 de junio",
      "url": "https://www.elperiodicoextremadura.com/tiempo/2026/06/30/tiempo-jaraiz-vera-prevision-meteorologica-131953655.html",
      "imagen": "https://estaticos-cdn.prensaiberica.es/clip/66a0fa5f-c649-4c3b-bba8-85edf6addef3_16-9-aspect-ratio_default_0_x600y225.jpg",
      "fecha": "2026-06-30T01:59:20.000Z",
      "fuenteId": "el-periodico-extremadura",
      "fuenteTitle": "El Periódico Extremadura",
      "categorias": [
        "local"
      ],
      "idioma": "es"
    },
    {
      "titulo": "El tiempo en Talayuela: previsión meteorológica para hoy, martes 30 de junio",
      "url": "https://www.elperiodicoextremadura.com/tiempo/2026/06/30/tiempo-talayuela-prevision-meteorologica-hoy-131953653.html",
      "imagen": "https://estaticos-cdn.prensaiberica.es/clip/c7f3570b-ca82-4cc8-973c-7f27d3c4a969_16-9-aspect-ratio_default_0_x600y225.jpg",
      "fecha": "2026-06-30T01:59:07.000Z",
      "fuenteId": "el-periodico-extremadura",
      "fuenteTitle": "El Periódico Extremadura",
      "categorias": [
        "local"
      ],
      "idioma": "es"
    },
    {
      "titulo": "El director ejecutivo de Legend Biotech, Huang Ying, vende 82.265 dólares en acciones",
      "url": "https://es.investing.com/news/insider-trading-news/el-director-ejecutivo-de-legend-biotech-huang-ying-vende-82265-dolares-en-acciones-93CH-3721615",
      "imagen": "https://i-invdn-com.investing.com/news/world_news_2_108x81.jpg",
      "fecha": "2026-06-30T01:58:43.000Z",
      "fuenteId": "investing-es-noticias",
      "fuenteTitle": "Investing.com España - Noticias",
      "categorias": [
        "economia"
      ],
      "idioma": "es"
    },
    {
      "titulo": "El tiempo en Navalmoral de la Mata: previsión meteorológica para hoy, martes 30 de junio",
      "url": "https://www.elperiodicoextremadura.com/tiempo/2026/06/30/tiempo-navalmoral-mata-prevision-meteorologica-131953635.html",
      "imagen": "https://estaticos-cdn.prensaiberica.es/clip/10b007a6-0d26-4b00-997c-a0e5f9c2c7d7_16-9-aspect-ratio_default_0_x600y225.jpg",
      "fecha": "2026-06-30T01:57:40.000Z",
      "fuenteId": "el-periodico-extremadura",
      "fuenteTitle": "El Periódico Extremadura",
      "categorias": [
        "local"
      ],
      "idioma": "es"
    },
    {
      "titulo": "El tiempo en Trujillo: previsión meteorológica para hoy, martes 30 de junio",
      "url": "https://www.elperiodicoextremadura.com/tiempo/2026/06/30/tiempo-trujillo-prevision-meteorologica-hoy-131953633.html",
      "imagen": "https://estaticos-cdn.prensaiberica.es/clip/a98b8aba-9e17-47ed-8c75-d5cd948ce11c_16-9-aspect-ratio_default_0_x600y225.jpg",
      "fecha": "2026-06-30T01:57:29.000Z",
      "fuenteId": "el-periodico-extremadura",
      "fuenteTitle": "El Periódico Extremadura",
      "categorias": [
        "local"
      ],
      "idioma": "es"
    },
    {
      "titulo": "Trump exige una bajada inmediata de la gasolina y fija un objetivo: 2,50 dólares por galón",
      "url": "https://www.huffingtonpost.es/global/trump-exige-bajada-inmediata-gasolina-fija-objetivo-250-dolares-galon-f202606.html",
      "imagen": "",
      "fecha": "2026-06-30T01:54:27.000Z",
      "fuenteId": "huffpost-espana",
      "fuenteTitle": "HuffPost España",
      "categorias": [
        "actualidad",
        "entretenimiento"
      ],
      "idioma": "es"
    },
    {
      "titulo": "Curbline Properties fija una oferta de acciones por 308,5 millones de dólares",
      "url": "https://es.investing.com/news/company-news/curbline-properties-fija-una-oferta-de-acciones-por-3085-millones-de-dolares-93CH-3721611",
      "imagen": "https://i-invdn-com.investing.com/news/world_news_2_108x81.jpg",
      "fecha": "2026-06-30T01:52:07.000Z",
      "fuenteId": "investing-es-noticias",
      "fuenteTitle": "Investing.com España - Noticias",
      "categorias": [
        "economia"
      ],
      "idioma": "es"
    },
    {
      "titulo": "El presidente de Paraguay decreta feriado para celebrar la clasificación de a octavos de final",
      "url": "https://www.cope.es/programas/tiempo-de-juego/noticias/presidente-paraguay-decreta-feriado-celebrar-clasificacion-octavos-final-20260630_3394052.html",
      "imagen": "https://imagenes.cope.es/files/og_thumbnail/uploads/2026/06/30/6a43207749c94.jpeg",
      "fecha": "2026-06-30T01:49:44.000Z",
      "fuenteId": "cope-extremadura",
      "fuenteTitle": "COPE Extremadura",
      "categorias": [
        "local"
      ],
      "idioma": "es"
    },
    {
      "titulo": "El uso que Barrabés hizo de las palabras de Sánchez añade un elemento clave a la influencia que Begoña ejerció a su favor",
      "url": "https://www.elespanol.com/espana/tribunales/20260630/uso-barrabes-hizo-palabras-sanchez-anade-elemento-clave-influencia-begona-ejercio-favor/1003744304387_0.html",
      "imagen": "https://s3.elespanol.com/k/imgp/cms/elespanol/11304849.jpg?p=w:1706/h:960&h=nEIcTIKQ",
      "fecha": "2026-06-30T01:48:13.000Z",
      "fuenteId": "el-espanol",
      "fuenteTitle": "El Español",
      "categorias": [
        "actualidad"
      ],
      "idioma": "es"
    },
    {
      "titulo": "Diego Lorenzo, el español de 15 años fallecido en el terremoto de Venezuela: \"Murió con dos amigos, estaban abrazados\"",
      "url": "https://www.elespanol.com/reportajes/20260630/diego-lorenzo-espanol-anos-fallecido-terremoto-venezuela-murio-amigos-abrazados/1003744304235_0.html",
      "imagen": "https://s3.elespanol.com/k/imgp/cms/elespanol/11304799.jpg?p=w:1706/h:960&h=1uzGegY7",
      "fecha": "2026-06-30T01:48:13.000Z",
      "fuenteId": "el-espanol",
      "fuenteTitle": "El Español",
      "categorias": [
        "actualidad"
      ],
      "idioma": "es"
    },
    {
      "titulo": "Extranjería tenía razón: las solicitudes de regularización de migrantes rozan los 1,3 M frente a los 500.000 que dijo Sánchez",
      "url": "https://www.elespanol.com/espana/20260630/extranjeria-razon-solicitudes-regularizacion-migrantes-rozan-frente-dijo-sanchez/1003744304190_0.html",
      "imagen": "https://s3.elespanol.com/k/imgp/cms/elespanol/11304788.jpg?p=w:1706/h:960&h=7zMLk95P",
      "fecha": "2026-06-30T01:48:11.000Z",
      "fuenteId": "el-espanol",
      "fuenteTitle": "El Español",
      "categorias": [
        "actualidad"
      ],
      "idioma": "es"
    },
    {
      "titulo": "SpaceX, boicot demócrata y una vaca llamada Melania: así es la feria MAGA con la que Trump celebra los 250 años de EEUU",
      "url": "https://www.elespanol.com/mundo/america/eeuu/20260630/spacex-boicot-democrata-vaca-llamada-melania-feria-maga-trump-celebra-anos-eeuu/1003744304189_0.html",
      "imagen": "https://s3.elespanol.com/k/imgp/cms/elespanol/11304736.jpg?p=c:3997:2254:nowe:0:0/w:1706/h:960&h=TByHmYXd",
      "fecha": "2026-06-30T01:48:11.000Z",
      "fuenteId": "el-espanol",
      "fuenteTitle": "El Español",
      "categorias": [
        "actualidad"
      ],
      "idioma": "es"
    },
    {
      "titulo": "Belén Gualda, la otra protegida de María Jesús Montero: tras los pasos de Vicente Fernández con 258.785€ de sueldo",
      "url": "https://www.elespanol.com/reportajes/20260630/belen-gualda-protegida-maria-jesus-montero-pasos-vicente-fernandez-sueldo/1003744304182_0.html",
      "imagen": "https://s3.elespanol.com/k/imgp/cms/elespanol/11304773.jpg?p=w:1706/h:960&h=bDexbBqB",
      "fecha": "2026-06-30T01:48:10.000Z",
      "fuenteId": "el-espanol",
      "fuenteTitle": "El Español",
      "categorias": [
        "actualidad"
      ],
      "idioma": "es"
    },
    {
      "titulo": "Vox enfría las expectativas de Juanma Moreno tras la primera sesión de investidura sin guiños a la \"prioridad nacional\"",
      "url": "https://www.elespanol.com/espana/andalucia/20260630/vox-enfria-expectativas-juanma-moreno-primera-sesion-investidura-sin-guinos-prioridad-nacional/1003744304045_0.html",
      "imagen": "https://s3.elespanol.com/k/imgp/cms/elespanol/11304627.jpg?p=w:1706/h:960&h=xeL5PjuD",
      "fecha": "2026-06-30T01:48:09.000Z",
      "fuenteId": "el-espanol",
      "fuenteTitle": "El Español",
      "categorias": [
        "actualidad"
      ],
      "idioma": "es"
    },
    {
      "titulo": "Jarillo-Herrero, el físico español en las quinielas para el Nobel: \"Hace falta que nuestra clase política esté mejor educada\"",
      "url": "https://www.elespanol.com/ciencia/investigacion/20260630/jarillo-herrero-fisico-espanol-quinielas-nobel-hace-falta-clase-politica-mejor-educada/1003744304052_0.html",
      "imagen": "https://s3.elespanol.com/k/imgp/cms/elespanol/11304675.jpg?p=c:4000:2253:nowe:0:185/w:1706/h:960&h=qdc277OT",
      "fecha": "2026-06-30T01:48:09.000Z",
      "fuenteId": "el-espanol-ciencia",
      "fuenteTitle": "El Español - Ciencia",
      "categorias": [
        "ciencia",
        "salud"
      ],
      "idioma": "es"
    }
  ]
}
